stacksense/__init__.py
stacksense/agents/__init__.py
stacksense/agents/file_selector_agent.py
stacksense/agents/memory_writer_agent.py
stacksense/agents/slice_extractor_agent.py
stacksense/api/__init__.py
stacksense/api/main.py
stacksense/api/prompts.py
stacksense/backend/__init__.py
stacksense/backend/database.py
stacksense/backend/license_signer.py
stacksense/backend/main.py
stacksense/backend/models.py
stacksense/backend/schemas.py
stacksense/backend/utils.py
stacksense/backend/webhooks.py
stacksense/cli/__init__.py
stacksense/cli/chat.py
stacksense/cli/cli.py
stacksense/cli/commands.py
stacksense/cli/completer.py
stacksense/cli/config_manager.py
stacksense/cli/rich_chat.py
stacksense/cli/terminal_ui.py
stacksense/cli/ui_utils.py
stacksense/core/__init__.py
stacksense/core/adaptive_scanner.py
stacksense/core/agent.py
stacksense/core/ai_guided_reader.py
stacksense/core/base_agent.py
stacksense/core/cache_manager.py
stacksense/core/citation_fixer.py
stacksense/core/code_extractor.py
stacksense/core/config.py
stacksense/core/context_adapter.py
stacksense/core/context_builder.py
stacksense/core/context_formatter.py
stacksense/core/context_health.py
stacksense/core/credentials.py
stacksense/core/diagram_builder.py
stacksense/core/diagram_keyword_extractor.py
stacksense/core/diagram_orchestrator.py
stacksense/core/diagram_to_text.py
stacksense/core/domain_learner.py
stacksense/core/fast_query_processor.py
stacksense/core/framework_aware_filter.py
stacksense/core/framework_detector.py
stacksense/core/grep_searcher.py
stacksense/core/grok_agent.py
stacksense/core/keyword_extractor.py
stacksense/core/language_detector.py
stacksense/core/model_manager.py
stacksense/core/module_summarizer.py
stacksense/core/native_agent.py
stacksense/core/openai_agent.py
stacksense/core/openrouter_agent.py
stacksense/core/openrouter_client.py
stacksense/core/prompt_engineer.py
stacksense/core/query_learner.py
stacksense/core/rate_limiter.py
stacksense/core/relationship_mapper.py
stacksense_cli-0.1.3.dist-info/licenses/LICENSE.md
stacksense_cli-0.1.3.dist-info/METADATA
stacksense_cli-0.1.3.dist-info/WHEEL
stacksense_cli-0.1.3.dist-info/entry_points.txt
stacksense_cli-0.1.3.dist-info/top_level.txt
stacksense_cli-0.1.3.dist-info/RECORD
