Metadata-Version: 2.4
Name: stacksense-cli
Version: 0.1.3
Summary: AI-powered code intelligence for developers
Home-page: https://portfolio-pied-five-61.vercel.app/
Author: PilgrimStack
Author-email: PilgrimStack <dev@stacksense.dev>
License-Expression: LicenseRef-Proprietary
Project-URL: Homepage, https://stacksense-docs.vercel.app
Project-URL: Documentation, https://stacksense-docs.vercel.app
Project-URL: Repository, https://github.com/AmariahAK/Stacksense
Keywords: ai,code-analysis,developer-tools,cli,llm
Classifier: Development Status :: 4 - Beta
Classifier: Environment :: Console
Classifier: Intended Audience :: Developers
Classifier: Operating System :: OS Independent
Classifier: Programming Language :: Python :: 3
Classifier: Programming Language :: Python :: 3.8
Classifier: Programming Language :: Python :: 3.9
Classifier: Programming Language :: Python :: 3.10
Classifier: Programming Language :: Python :: 3.11
Classifier: Programming Language :: Python :: 3.12
Classifier: Topic :: Software Development
Classifier: Topic :: Software Development :: Code Generators
Requires-Python: >=3.8
License-File: LICENSE.md
Requires-Dist: openai
Requires-Dist: httpx
Requires-Dist: rich
Requires-Dist: prompt_toolkit
Requires-Dist: colorama
Requires-Dist: ddgs
Requires-Dist: newspaper3k
Requires-Dist: requests
Requires-Dist: readability-lxml
Requires-Dist: lxml[html_clean]
Requires-Dist: networkx
Requires-Dist: graphviz
Requires-Dist: scikit-learn
Requires-Dist: numpy
Requires-Dist: fastapi
Requires-Dist: uvicorn
Requires-Dist: aiohttp
Requires-Dist: aiofiles
Requires-Dist: python-dotenv
Requires-Dist: packaging
Requires-Dist: markdown
Requires-Dist: pydantic
Requires-Dist: cryptography
Requires-Dist: click
Provides-Extra: parsing
Requires-Dist: tree-sitter>=0.21.3; extra == "parsing"
Requires-Dist: tree-sitter-languages>=1.10.2; extra == "parsing"
Provides-Extra: full
Requires-Dist: tree-sitter>=0.21.3; extra == "full"
Requires-Dist: tree-sitter-languages>=1.10.2; extra == "full"
Provides-Extra: dev
Requires-Dist: pytest>=7.0.0; extra == "dev"
Requires-Dist: Cython>=0.29; extra == "dev"
Requires-Dist: build; extra == "dev"
Dynamic: author
Dynamic: home-page
Dynamic: license-file
Dynamic: requires-python
